HuggingMouse/__init__.py
HuggingMouse/allen_api_utilities.py
HuggingMouse/custom_exceptions.py
HuggingMouse/make_embeddings.py
HuggingMouse/regressors.py
HuggingMouse/trial_averaged_data.py
HuggingMouse/utils.py
HuggingMouse/visualizers.py
HuggingMouse/pipelines/__init__.py
HuggingMouse/pipelines/base.py
HuggingMouse/pipelines/neuron_prediction.py
HuggingMouse/pipelines/pipeline_tasks.py
HuggingMouse/pipelines/pipelines.py
HuggingMouse/pipelines/single_trial_fs.py
HuggingMouse-0.2.0.dist-info/LICENSE
HuggingMouse-0.2.0.dist-info/METADATA
HuggingMouse-0.2.0.dist-info/WHEEL
HuggingMouse-0.2.0.dist-info/top_level.txt
HuggingMouse-0.2.0.dist-info/RECORD
